lektor_qiniu.py
lektor_qiniu-0.1.3.dist-info/METADATA
lektor_qiniu-0.1.3.dist-info/WHEEL
lektor_qiniu-0.1.3.dist-info/entry_points.txt
lektor_qiniu-0.1.3.dist-info/top_level.txt
lektor_qiniu-0.1.3.dist-info/RECORD
